aisolutions/__init__.py
aisolutions/config.py
aisolutions/get_image_description.py
aisolutions/open_ai_client.py
aisolutions-0.1.7.dist-info/LICENSE
aisolutions-0.1.7.dist-info/METADATA
aisolutions-0.1.7.dist-info/WHEEL
aisolutions-0.1.7.dist-info/top_level.txt
aisolutions-0.1.7.dist-info/RECORD
